LICENSE.txt
README.md
setup.cfg
setup.py
update_lib_code
py_topping/__init__.py
py_topping.egg-info/PKG-INFO
py_topping.egg-info/SOURCES.txt
py_topping.egg-info/dependency_links.txt
py_topping.egg-info/top_level.txt
py_topping/data_connection/__init__.py
py_topping/data_connection/database.py
py_topping/data_connection/database_old.py
py_topping/data_connection/opc.py
py_topping/data_connection/sftp.py
py_topping/data_connection/sharepoint.py
py_topping/data_connection/sharepoint_old.py
py_topping/data_connection/socket.py
py_topping/data_connection/aws/__init__.py
py_topping/data_connection/aws/s3.py
py_topping/data_connection/gcp/__init__.py
py_topping/data_connection/gcp/gbq.py
py_topping/data_connection/gcp/gcs.py
py_topping/data_preparation/__init__.py
py_topping/data_preparation/lazy_ml.py
py_topping/general_use/__init__.py
py_topping/image_processing/__init__.py
py_topping/run_pipeline/__init__.py
py_topping/run_pipeline/api.py
py_topping/run_pipeline/test.py
samples/api.ipynb
samples/data_preparation.ipynb
samples/database.ipynb
samples/email_sender.ipynb
samples/lazy_LINE.ipynb
samples/lazy_OPCUA.ipynb
samples/lazy_SFTP.ipynb
samples/lazy_TCP.ipynb
samples/lazy_ml.ipynb
samples/other_function.ipynb
samples/run_pipeline.ipynb
samples/sharepoint.ipynb
samples/integrated/db_to_db/Dockerfile
samples/integrated/db_to_db/main.py
samples/integrated/db_to_gcs/Dockerfile
samples/integrated/db_to_gcs/main.py
samples/integrated/db_to_sftp/Dockerfile
samples/integrated/db_to_sftp/main.py
samples/integrated/sp365_to_db/Dockerfile
samples/integrated/sp365_to_db/main.py
samples/integrated/sp365_to_db/requirements.txt
tests/database.ipynb
tests/gcp.ipynb