Metadata-Version: 2.4
Name: py_topping
Version: 0.4.13
Summary: simplify functions from other libraries functions in 1-2 lines
Home-page: https://github.com/chanon-kr/Shared_Function
Download-URL: https://github.com/chanon-kr/Shared_Function/archive/v0.4.11.tar.gz
Author: Chanon Krittapholchai
Author-email: chanon.krittapholchai@gmail.com
License: MIT
Keywords: utility,ETL
Classifier: Development Status :: 4 - Beta
Classifier: Programming Language :: Python :: 3
Classifier: License :: OSI Approved :: MIT License
Requires-Python: >=3.6
License-File: LICENSE.txt
Dynamic: author
Dynamic: author-email
Dynamic: classifier
Dynamic: description
Dynamic: description-content-type
Dynamic: download-url
Dynamic: home-page
Dynamic: keywords
Dynamic: license
Dynamic: license-file
Dynamic: requires-python
Dynamic: summary
